annotell_query-2.5.0-py3.8-nspkg.pth
annotell/query/__init__.py
annotell/query/query_api_client.py
annotell/query/query_model.py
annotell/query/util.py
annotell_query-2.5.0.dist-info/METADATA
annotell_query-2.5.0.dist-info/WHEEL
annotell_query-2.5.0.dist-info/namespace_packages.txt
annotell_query-2.5.0.dist-info/top_level.txt
annotell_query-2.5.0.dist-info/RECORD
