Metadata-Version: 2.1
Name: annotell-query
Version: 2.5.0
Summary: Annotell Query API Client
Home-page: https://github.com/annotell/annotell-python
Download-URL: https://github.com/annotell/annotell-python/tarball/2.5.0
Author: Annotell
Author-email: Michel Edkrantz <michel.edkrantz@annotell.com>
License: MIT
Keywords: API,Annotell
Platform: UNKNOWN
Classifier: Development Status :: 5 - Production/Stable
Classifier: License :: OSI Approved :: MIT License
Classifier: Intended Audience :: Developers
Classifier: Programming Language :: Python :: 3
Requires-Python: ~=3.6
Requires-Dist: requests (<3,>=2.20)
Requires-Dist: annotell-auth[requests] (<3,>=2.0.0)
